llm_sentence_transformers.py
llm_sentence_transformers-0.3.2.dist-info/licenses/LICENSE
llm_sentence_transformers-0.3.2.dist-info/METADATA
llm_sentence_transformers-0.3.2.dist-info/WHEEL
llm_sentence_transformers-0.3.2.dist-info/entry_points.txt
llm_sentence_transformers-0.3.2.dist-info/top_level.txt
llm_sentence_transformers-0.3.2.dist-info/RECORD
