Metadata-Version: 2.4
Name: llm-sentence-transformers
Version: 0.3.2
Summary: Use sentence-transformers for embeddings with LLM
Author: Simon Willison
License: Apache-2.0
Project-URL: Homepage, https://github.com/simonw/llm-sentence-transformers
Project-URL: Changelog, https://github.com/simonw/llm-sentence-transformers/releases
Project-URL: Issues, https://github.com/simonw/llm-sentence-transformers/issues
Project-URL: CI, https://github.com/simonw/llm-sentence-transformers/actions
Classifier: License :: OSI Approved :: Apache Software License
License-File: LICENSE
Requires-Dist: llm>=0.9
Requires-Dist: sentence-transformers
Requires-Dist: einops
Provides-Extra: test
Requires-Dist: pytest; extra == "test"
Dynamic: license-file
